{
	"components": [{
		"name": "hotkey_manager:btn",
		"keys": [{
			"keyname": "hotkey_manager:enter_space",
			"fn": "hotkey_manager:btn_enter_space"
		}]
	}, {
		"name": "hotkey_manager:menu",
		"keys": [{
			"keyname": "hotkey_manager:up_down",
			"fn": "hotkey_manager:menu_up_down"
		}, {
			"keyname": "hotkey_manager:right",
			"fn": "hotkey_manager:menu_right"
		}, {
			"keyname": "hotkey_manager:left",
			"fn": "hotkey_manager:menu_left"
		}]
	}, {
		"name": "hotkey_manager:combo",
		"keys": [{
			"keyname": "hotkey_manager:down",
			"fn": "hotkey_manager:combo_down"
		}, {
			"keyname": "hotkey_manager:up_down",
			"fn": "hotkey_manager:combo_up_down"
		}, {
			"keyname": "hotkey_manager:enter",
			"fn": "hotkey_manager:combo_enter"
		}, {
			"keyname": "hotkey_manager:esc",
			"fn": "hotkey_manager:combo_esc"
		}]
	}, {
		"name": "hotkey_manager:date",
		"keys": [{
			"keyname": "hotkey_manager:arrow",
			"fn": "hotkey_manager:date_arrow"
		}, {
			"keyname": "hotkey_manager:left_right_shift",
			"fn": "hotkey_manager:date_left_right_shift"
		}, {
			"keyname": "hotkey_manager:up_down_shift",
			"fn": "hotkey_manager:date_up_down_shift"
		}, {
			"keyname": "hotkey_manager:enter",
			"fn": "hotkey_manager:date_enter"
		}, {
			"keyname": "hotkey_manager:space",
			"fn": "hotkey_manager:date_space"
		}]
	}, {
		"name": "hotkey_manager:checkbox",
		"keys": [{
			"keyname": "hotkey_manager:space",
			"fn": "hotkey_manager:checkbox_space"
		}]
	}, {
		"name": "hotkey_manager:radio",
		"keys": [{
			"keyname": "hotkey_manager:arrow",
			"fn": "hotkey_manager:radio_arrow"
		}]
	}, {
		"name": "hotkey_manager:search",
		"keys": [{
			"keyname": "hotkey_manager:enter",
			"fn": "hotkey_manager:search_enter"
		}, {
			"keyname": "hotkey_manager:up_down",
			"fn": "hotkey_manager:search_up_down"
		}]
	}, {
		"name": "hotkey_manager:grid",
		"keys": [{
			"keyname": "hotkey_manager:left_right",
			"fn": "hotkey_manager:grid_left_right"
		}, {
			"keyname": "hotkey_manager:up_down",
			"fn": "hotkey_manager:grid_up_down"
		}, {
			"keyname": "hotkey_manager:space",
			"fn": "hotkey_manager:grid_space"
		}]
	}, {
		"name": "hotkey_manager:tree",
		"keys": [{
			"keyname": "hotkey_manager:left",
			"fn": "hotkey_manager:tree_left"
		}, {
			"keyname": "hotkey_manager:right",
			"fn": "hotkey_manager:tree_right"
		}, {
			"keyname": "hotkey_manager:up_down",
			"fn": "hotkey_manager:tree_up_down"
		}]
	}, {
		"name": "hotkey_manager:tabpanel",
		"keys": [{
			"keyname": "hotkey_manager:left_right",
			"fn": "hotkey_manager:tabpanel_left_right"
		}, {
			"keyname": "hotkey_manager:tab",
			"fn": "hotkey_manager:tabpanel_tab"
		}]
	}, {
		"name": "hotkey_manager:list",
		"keys": [{
			"keyname": "hotkey_manager:arrow",
			"fn": "hotkey_manager:list_arrow"
		}]
	}]
}